unitlog/__init__.py
unitlog/handlers.py
unitlog/unit.py
unitlog/util_log.py
unitlog-0.0.4.dist-info/licenses/LICENSE
unitlog-0.0.4.dist-info/METADATA
unitlog-0.0.4.dist-info/WHEEL
unitlog-0.0.4.dist-info/top_level.txt
unitlog-0.0.4.dist-info/RECORD
