Metadata-Version: 2.4
Name: unitlog
Version: 0.0.4
Home-page: https://github.com/yujun2647/unitlog
Download-URL: 
Author: walkerjun
Author-email: yujun2647@163.com
License: Apache-2.0
Requires-Python: >=3.6
License-File: LICENSE
Dynamic: author
Dynamic: author-email
Dynamic: description
Dynamic: description-content-type
Dynamic: home-page
Dynamic: license
Dynamic: license-file
Dynamic: requires-python
